repcloud/__init__.py
repcloud/gen_lib.py
repcloud/pg_lib.py
repcloud/repack_lib.py
repcloud/config/config-example.toml
repcloud/config/config-example_repack.toml
repcloud/sql/create_schema.sql
repcloud/sql/drop_schema.sql
repcloud-0.1a1.data/scripts/rpcl
repcloud-0.1a1.data/scripts/rpcl.py
repcloud-0.1a1.dist-info/LICENSE.txt
repcloud-0.1a1.dist-info/METADATA
repcloud-0.1a1.dist-info/WHEEL
repcloud-0.1a1.dist-info/top_level.txt
repcloud-0.1a1.dist-info/RECORD
