Metadata-Version: 2.1
Name: repcloud
Version: 0.1a1
Summary: PostgreSQL repacker without need
Home-page: https://github.com/the4thdoctor/repcloud/
Author: Federico Campoli
Author-email: the4thdoctor.gallifrey@gmail.com
Maintainer: Federico Campoli
Maintainer-email: the4thdoctor.gallifrey@gmail.com
License: BSD License
Keywords: postgresql database cloud repack transform
Platform: linux
Classifier: License :: OSI Approved :: BSD License
Classifier: Environment :: Console
Classifier: Intended Audience :: Developers
Classifier: Intended Audience :: Information Technology
Classifier: Intended Audience :: System Administrators
Classifier: Natural Language :: English
Classifier: Operating System :: POSIX :: BSD
Classifier: Operating System :: POSIX :: Linux
Classifier: Programming Language :: Python
Classifier: Programming Language :: Python :: 3
Classifier: Programming Language :: Python :: 3.3
Classifier: Programming Language :: Python :: 3.4
Classifier: Programming Language :: Python :: 3.5
Classifier: Programming Language :: Python :: 3.6
Classifier: Topic :: Database :: Database Engines/Servers
Classifier: Topic :: Other/Nonlisted Topic
Requires-Python: >=3.5
Requires-Dist: argparse (>=1.2.1)
Requires-Dist: psycopg2-binary (>=2.7.4)
Requires-Dist: toml (>=0.10.0)
Requires-Dist: tabulate (>=0.8.1)
Requires-Dist: daemonize (>=2.4.7)
Requires-Dist: sphinx (>=2.1.2)
